{
    "number": "656226",
    "isOpen": "Open",
    "startingTraiderCapital": "500.00 USD",
    "currentTraiderCapital": "362.29 USD",
    "investorsCapital": "10.00 USD",
    "ralativeDropdown": "25.64%",
    "maxDropdown": "15.10%",
    "openTraidsCount": "2",
    "expectedAnnualProfit": "-721.50%",
    "openOffertaDate": "23.09.2014 15:17",
    "firstRollowerDate": "27.09.2014 10:00",
    "previousRollowerDate": "27.09.2014 12:11",
    "nextRollowerDate": "04.10.2014 10:00",
    "monthlyProfit": [
        {
            "text": "September 2014",
            "profit": "50.00",
            "inverstorProfit": "10.30%"
        },
        {
            "text": "October 2014",
            "profit": "-190.10",
            "inverstorProfit": "-38.05%"
        }
    ],
    "weeklyProfit": [
        {
            "text": "22.09.2014 - 28.09.2014",
            "profit": "-11.80",
            "inverstorProfit": "-2.36%"
        },
        {
            "text": "29.09.2014 - 05.10.2014",
            "profit": "-128.30",
            "inverstorProfit": "-25.39%"
        }
    ]
}